utils/__init__.py
utils/pypi_api.py
utils/version_checker.py
vast.py
vastai-0.4.0.dist-info/METADATA
vastai-0.4.0.dist-info/WHEEL
vastai-0.4.0.dist-info/entry_points.txt
vastai-0.4.0.dist-info/licenses/LICENSE
vastai-0.4.0.dist-info/RECORD
