Metadata-Version: 2.4
Name: vastai
Version: 0.4.0
Summary: 
License: MIT
License-File: LICENSE
Author: jake cannell
Author-email: jake@vast.ai
Requires-Python: >3.9.1, <4.0
Classifier: License :: OSI Approved :: MIT License
Classifier: Programming Language :: Python :: 3
Classifier: Programming Language :: Python :: 3.10
Classifier: Programming Language :: Python :: 3.11
Classifier: Programming Language :: Python :: 3.12
Classifier: Programming Language :: Python :: 3.13
Classifier: Programming Language :: Python :: 3.14
Requires-Dist: argcomplete (==3.5.1)
Requires-Dist: borb (==2.1.25)
Requires-Dist: cryptography (>=44.0.2,<45.0.0)
Requires-Dist: curlify (>=2.2.1,<3.0.0)
Requires-Dist: gitpython (>=3.1.44,<4.0.0)
Requires-Dist: poetry-dynamic-versioning (>=1.8.1,<2.0.0)
Requires-Dist: python-dateutil (==2.6.1)
Requires-Dist: pytz
Requires-Dist: requests (>=2.32.4)
Requires-Dist: setuptools
Requires-Dist: toml (>=0.10.2,<0.11.0)
Requires-Dist: urllib3 (>=2.5.0)
Requires-Dist: xdg
Project-URL: Homepage, https://cloud.vast.ai/
Project-URL: Repository, https://github.com/vast-ai/vast-cli/
